AUTHORS
CHANGES
LICENSE
MANIFEST.in
README.rst
run_tests.py
setup.cfg
setup.py
docs/Makefile
docs/builtin_filters.rst
docs/bundles.rst
docs/conf.py
docs/css_compilers.rst
docs/custom_filters.rst
docs/environment.rst
docs/expiring.rst
docs/faq.rst
docs/index.rst
docs/loaders.rst
docs/make.bat
docs/renderer.rst
docs/script.rst
docs/upgrading.rst
docs/generic/custom_resolver.rst
docs/generic/index.rst
docs/integration/index.rst
docs/integration/jinja2.rst
examples/appengine/README
examples/appengine/app.yaml
examples/appengine/assets.py
examples/appengine/helloworld.py
examples/no-python/README.rst
examples/no-python/bundles.yaml
src/webassets/__init__.py
src/webassets/bundle.py
src/webassets/cache.py
src/webassets/env.py
src/webassets/exceptions.py
src/webassets/importlib.py
src/webassets/loaders.py
src/webassets/merge.py
src/webassets/renderer.py
src/webassets/script.py
src/webassets/six.py
src/webassets/test.py
src/webassets/updater.py
src/webassets/utils.py
src/webassets/version.py
src/webassets/ext/__init__.py
src/webassets/ext/jinja2.py
src/webassets/filter/__init__.py
src/webassets/filter/autoprefixer.py
src/webassets/filter/cleancss.py
src/webassets/filter/clevercss.py
src/webassets/filter/closure.py
src/webassets/filter/closure_templates.py
src/webassets/filter/coffeescript.py
src/webassets/filter/compass.py
src/webassets/filter/cssmin.py
src/webassets/filter/cssprefixer.py
src/webassets/filter/cssutils.py
src/webassets/filter/datauri.py
src/webassets/filter/dust.py
src/webassets/filter/handlebars.py
src/webassets/filter/jade.py
src/webassets/filter/jinja2.py
src/webassets/filter/jsmin.py
src/webassets/filter/jst.py
src/webassets/filter/less.py
src/webassets/filter/less_ruby.py
src/webassets/filter/pyscss.py
src/webassets/filter/requirejs.py
src/webassets/filter/sass.py
src/webassets/filter/slimmer.py
src/webassets/filter/spritemapper.py
src/webassets/filter/stylus.py
src/webassets/filter/typescript.py
src/webassets/filter/uglifyjs.py
src/webassets2.egg-info/PKG-INFO
src/webassets2.egg-info/SOURCES.txt
src/webassets2.egg-info/dependency_links.txt
src/webassets2.egg-info/entry_points.txt
src/webassets2.egg-info/top_level.txt
