Metadata-Version: 1.1
Name: webassets2
Version: 0.10.dev-fork-renderer.7
Summary: Media asset management for Python, with glue code for various web frameworks
Home-page: https://github.com/miracle2k/webassets/pull/283
Author: Michael Elsdoerfer
Author-email: michael@elsdoerfer.com
License: BSD
Platform: UNKNOWN
Classifier: Development Status :: 3 - Alpha
Classifier: Environment :: Web Environment
Classifier: Intended Audience :: Developers
Classifier: License :: OSI Approved :: BSD License
Classifier: Operating System :: OS Independent
Classifier: Programming Language :: Python
Classifier: Programming Language :: Python :: 3
Classifier: Topic :: Internet :: WWW/HTTP
Classifier: Topic :: Software Development :: Libraries
